LICENSE.txt
MANIFEST.in
README.md
setup.cfg
setup.py
django_fans_validator.egg-info/PKG-INFO
django_fans_validator.egg-info/SOURCES.txt
django_fans_validator.egg-info/dependency_links.txt
django_fans_validator.egg-info/top_level.txt
validator/__init__.py
validator/tests.py
validator/validators.py