Metadata-Version: 1.1
Name: django-fans-validator
Version: 1.0.4
Summary: a django request POST/GET data validator
Home-page: https://github.com/youngershen/django-contrib-validator
Author: Younger Shen
Author-email: younger.x.shen@gmail.com
License: MIT
Keywords: a django request POST/GET data validator
Platform: UNKNOWN
Classifier: Development Status :: 3 - Alpha
Classifier: Intended Audience :: Developers
Classifier: License :: OSI Approved :: MIT License
Classifier: Programming Language :: Python :: 3.6
